MANIFEST.in
setup.py
CME.egg-info/PKG-INFO
CME.egg-info/SOURCES.txt
CME.egg-info/dependency_links.txt
CME.egg-info/entry_points.txt
CME.egg-info/top_level.txt
script/CME.py
script/__init__.py
script/calibration_files/bandlist.txt
script/calibration_files/fluxcalib.txt
script/calibration_files/irsa_calib.txt