Metadata-Version: 1.0
Name: CME
Version: 1.0
Summary: GUI for interactive plotting of colour-magnitude and colour-colour diagrams
Home-page: UNKNOWN
Author: Jennifer Karr
Author-email: jkarr@asiaa.sinica.edu.tw
License: GNU public license
Platform: UNKNOWN
